company_fundamentals/__init__.py
company_fundamentals/fundamentals.py
company_fundamentals/utils.py
company_fundamentals/calculations/__init__.py
company_fundamentals/calculations/calculations.py
company_fundamentals/dev/__init__.py
company_fundamentals/dev/get_all_keys.py
company_fundamentals/mappings/__init__.py
company_fundamentals/mappings/mappings.py
company_fundamentals-0.0.6.dist-info/LICENSE
company_fundamentals-0.0.6.dist-info/METADATA
company_fundamentals-0.0.6.dist-info/WHEEL
company_fundamentals-0.0.6.dist-info/top_level.txt
company_fundamentals-0.0.6.dist-info/RECORD
