Metadata-Version: 2.1
Name: company-fundamentals
Version: 0.0.6
Summary: A package to standardize XBRL into fundamentals data
License: MIT
License-File: LICENSE
